BroadcastingRelayClient.py
ObservingRelayClient.py
RelayClientBase.py
RelayService_pb2.py
RelayService_pb2_grpc.py
NP.Grpc.PythonRelayInterfaces-0.99.2.dist-info/LICENSE
NP.Grpc.PythonRelayInterfaces-0.99.2.dist-info/METADATA
NP.Grpc.PythonRelayInterfaces-0.99.2.dist-info/WHEEL
NP.Grpc.PythonRelayInterfaces-0.99.2.dist-info/top_level.txt
NP.Grpc.PythonRelayInterfaces-0.99.2.dist-info/RECORD
