Metadata-Version: 2.1
Name: NP.Grpc.PythonRelayInterfaces
Version: 0.99.2
Summary: Python interface for the Relay Server Client
Author-email: "Nick Polya, Ph.D." <nick.polyak@verizon.net>
Project-URL: Homepage, https://github.com/npolyak/NP.Grpc.RelayServer/tree/main/NP.Grpc.PythonRelayInterfaces
Project-URL: Bug Tracker, https://github.com/npolyak/NP.Grpc.RelayServer/issues
Classifier: Programming Language :: Python :: 3
Classifier: License :: OSI Approved :: MIT License
Classifier: Operating System :: OS Independent
Requires-Python: >=3.7
License-File: LICENSE
